<?xml version="1.0" encoding="UTF-8"?>
<export version="D">
  <design>
    <source>/home/guy/aProjects/Solar charger/Harry/async/schematic/async.sch</source>
    <date>Thu 24 May 2018 13:54:10 AEST</date>
    <tool>Eeschema 4.0.7</tool>
    <sheet number="1" name="/" tstamps="/">
      <title_block>
        <title>Solar Charger Async</title>
        <company>farmerkeith</company>
        <rev/>
        <date>2018-05-19</date>
        <source>async.sch</source>
        <comment number="1" value=""/>
        <comment number="2" value=""/>
        <comment number="3" value=""/>
        <comment number="4" value=""/>
      </title_block>
    </sheet>
  </design>
  <components>
    <comp ref="J2">
      <value>Solar panel</value>
      <libsource lib="conn" part="Screw_Terminal_01x02"/>
      <sheetpath names="/" tstamps="/"/>
      <tstamp>5AF665D2</tstamp>
    </comp>
    <comp ref="J3">
      <value>Battery</value>
      <libsource lib="conn" part="Screw_Terminal_01x02"/>
      <sheetpath names="/" tstamps="/"/>
      <tstamp>5AF665D3</tstamp>
    </comp>
    <comp ref="R2">
      <value>100K</value>
      <libsource lib="device" part="R"/>
      <sheetpath names="/" tstamps="/"/>
      <tstamp>5AF665D5</tstamp>
    </comp>
    <comp ref="R6">
      <value>15K</value>
      <libsource lib="device" part="R"/>
      <sheetpath names="/" tstamps="/"/>
      <tstamp>5AF665D6</tstamp>
    </comp>
    <comp ref="C9">
      <value>100nF</value>
      <libsource lib="device" part="C"/>
      <sheetpath names="/" tstamps="/"/>
      <tstamp>5AF665D7</tstamp>
    </comp>
    <comp ref="C1.1">
      <value>100uF</value>
      <libsource lib="device" part="CP"/>
      <sheetpath names="/" tstamps="/"/>
      <tstamp>5AF665DA</tstamp>
    </comp>
    <comp ref="C1.3">
      <value>100uF</value>
      <libsource lib="device" part="CP"/>
      <sheetpath names="/" tstamps="/"/>
      <tstamp>5AF665DB</tstamp>
    </comp>
    <comp ref="C1.5">
      <value>100uF</value>
      <libsource lib="device" part="CP"/>
      <sheetpath names="/" tstamps="/"/>
      <tstamp>5AF665DC</tstamp>
    </comp>
    <comp ref="C1.7">
      <value>100uF</value>
      <libsource lib="device" part="CP"/>
      <sheetpath names="/" tstamps="/"/>
      <tstamp>5AF665DD</tstamp>
    </comp>
    <comp ref="U1">
      <value>ACS712module</value>
      <libsource lib="Modules" part="ACS712module"/>
      <sheetpath names="/" tstamps="/"/>
      <tstamp>5AF665DE</tstamp>
    </comp>
    <comp ref="F1">
      <value>Fuse_20A</value>
      <libsource lib="device" part="Fuse"/>
      <sheetpath names="/" tstamps="/"/>
      <tstamp>5AF665E0</tstamp>
    </comp>
    <comp ref="BT1">
      <value>Battery_FLA_+12V_120AH</value>
      <libsource lib="device" part="Battery"/>
      <sheetpath names="/" tstamps="/"/>
      <tstamp>5AF665E1</tstamp>
    </comp>
    <comp ref="J1">
      <value>LOAD</value>
      <libsource lib="conn" part="Screw_Terminal_01x02"/>
      <sheetpath names="/" tstamps="/"/>
      <tstamp>5AF665E2</tstamp>
    </comp>
    <comp ref="D8">
      <value>1N4148</value>
      <libsource lib="device" part="D_ALT"/>
      <sheetpath names="/" tstamps="/"/>
      <tstamp>5AF665E6</tstamp>
    </comp>
    <comp ref="U4">
      <value>DS18B20</value>
      <libsource lib="Modules" part="DS18B20"/>
      <sheetpath names="/" tstamps="/"/>
      <tstamp>5AF665E8</tstamp>
    </comp>
    <comp ref="J5">
      <value>Temperature</value>
      <libsource lib="conn" part="Screw_Terminal_01x03"/>
      <sheetpath names="/" tstamps="/"/>
      <tstamp>5AF665E9</tstamp>
    </comp>
    <comp ref="D2">
      <value>P6KE47CA</value>
      <libsource lib="device" part="D_TVS_ALT"/>
      <sheetpath names="/" tstamps="/"/>
      <tstamp>5AF665EB</tstamp>
    </comp>
    <comp ref="R1">
      <value>100K</value>
      <libsource lib="device" part="R"/>
      <sheetpath names="/" tstamps="/"/>
      <tstamp>5AF665EC</tstamp>
    </comp>
    <comp ref="R8">
      <value>10K</value>
      <libsource lib="device" part="R"/>
      <sheetpath names="/" tstamps="/"/>
      <tstamp>5AF665EE</tstamp>
    </comp>
    <comp ref="Q4">
      <value>2N3904</value>
      <libsource lib="device" part="Q_NPN_CBE"/>
      <sheetpath names="/" tstamps="/"/>
      <tstamp>5AF665EF</tstamp>
    </comp>
    <comp ref="R14">
      <value>100K</value>
      <libsource lib="device" part="R"/>
      <sheetpath names="/" tstamps="/"/>
      <tstamp>5AF665F0</tstamp>
    </comp>
    <comp ref="R15">
      <value>10K</value>
      <libsource lib="device" part="R"/>
      <sheetpath names="/" tstamps="/"/>
      <tstamp>5AF665F2</tstamp>
    </comp>
    <comp ref="Q9">
      <value>2N3904</value>
      <libsource lib="device" part="Q_NPN_CBE"/>
      <sheetpath names="/" tstamps="/"/>
      <tstamp>5AF665F3</tstamp>
    </comp>
    <comp ref="U5">
      <value>ACS712module</value>
      <libsource lib="Modules" part="ACS712module"/>
      <sheetpath names="/" tstamps="/"/>
      <tstamp>5AF66602</tstamp>
    </comp>
    <comp ref="R13">
      <value>100K</value>
      <libsource lib="device" part="R"/>
      <sheetpath names="/" tstamps="/"/>
      <tstamp>5AF66603</tstamp>
    </comp>
    <comp ref="R16">
      <value>47K</value>
      <libsource lib="device" part="R"/>
      <sheetpath names="/" tstamps="/"/>
      <tstamp>5AF66604</tstamp>
    </comp>
    <comp ref="U8">
      <value>MP2307_DC-DC_module</value>
      <libsource lib="Modules" part="MP2307_DC-DC_module"/>
      <sheetpath names="/" tstamps="/"/>
      <tstamp>5AF66605</tstamp>
    </comp>
    <comp ref="C5">
      <value>100nF</value>
      <libsource lib="device" part="C"/>
      <sheetpath names="/" tstamps="/"/>
      <tstamp>5AF66606</tstamp>
    </comp>
    <comp ref="U9">
      <value>LCDSerial2004</value>
      <libsource lib="Modules" part="LCDSerial2004"/>
      <sheetpath names="/" tstamps="/"/>
      <tstamp>5AF66609</tstamp>
    </comp>
    <comp ref="SW1">
      <value>Backlight control</value>
      <libsource lib="switches" part="SW_Push"/>
      <sheetpath names="/" tstamps="/"/>
      <tstamp>5AF6660B</tstamp>
    </comp>
    <comp ref="R17">
      <value>10K</value>
      <libsource lib="device" part="R"/>
      <sheetpath names="/" tstamps="/"/>
      <tstamp>5AF6660D</tstamp>
    </comp>
    <comp ref="Q8">
      <value>IRF4905</value>
      <footprint>TO_SOT_Packages_THT:TO-220_Vertical</footprint>
      <libsource lib="Modules" part="IRF4905"/>
      <sheetpath names="/" tstamps="/"/>
      <tstamp>5AF66612</tstamp>
    </comp>
    <comp ref="U11">
      <value>SD_Micro_5V</value>
      <libsource lib="Modules" part="SD_Micro_5V"/>
      <sheetpath names="/" tstamps="/"/>
      <tstamp>5AF66614</tstamp>
    </comp>
    <comp ref="U7">
      <value>DS1307_RTC</value>
      <libsource lib="Modules" part="DS1307_RTC"/>
      <sheetpath names="/" tstamps="/"/>
      <tstamp>5AF66616</tstamp>
    </comp>
    <comp ref="U6">
      <value>DS18B20</value>
      <libsource lib="Modules" part="DS18B20"/>
      <sheetpath names="/" tstamps="/"/>
      <tstamp>5AF66618</tstamp>
    </comp>
    <comp ref="J7">
      <value>Screw_Terminal_01x03</value>
      <libsource lib="conn" part="Screw_Terminal_01x03"/>
      <sheetpath names="/" tstamps="/"/>
      <tstamp>5AF66619</tstamp>
    </comp>
    <comp ref="D10">
      <value>GREEN LED</value>
      <libsource lib="device" part="LED_ALT"/>
      <sheetpath names="/" tstamps="/"/>
      <tstamp>5AF6661A</tstamp>
    </comp>
    <comp ref="D11">
      <value>RED LED</value>
      <libsource lib="device" part="LED_ALT"/>
      <sheetpath names="/" tstamps="/"/>
      <tstamp>5AF6661B</tstamp>
    </comp>
    <comp ref="R18">
      <value>470</value>
      <libsource lib="device" part="R"/>
      <sheetpath names="/" tstamps="/"/>
      <tstamp>5AF6661C</tstamp>
    </comp>
    <comp ref="R19">
      <value>470</value>
      <libsource lib="device" part="R"/>
      <sheetpath names="/" tstamps="/"/>
      <tstamp>5AF6661D</tstamp>
    </comp>
    <comp ref="U10">
      <value>ATMEGA328-PU</value>
      <footprint>DIL28</footprint>
      <libsource lib="atmel" part="ATMEGA328-PU"/>
      <sheetpath names="/" tstamps="/"/>
      <tstamp>5AF7134B</tstamp>
    </comp>
    <comp ref="D9">
      <value>GBJ1506</value>
      <libsource lib="device" part="D_Bridge_+-AA"/>
      <sheetpath names="/" tstamps="/"/>
      <tstamp>5AFA9C95</tstamp>
    </comp>
    <comp ref="J4">
      <value>Main voltage Screw Terminal</value>
      <libsource lib="conn" part="Screw_Terminal_01x03"/>
      <sheetpath names="/" tstamps="/"/>
      <tstamp>5AFAB716</tstamp>
    </comp>
    <comp ref="C3.1">
      <value>100uF</value>
      <libsource lib="device" part="CP"/>
      <sheetpath names="/" tstamps="/"/>
      <tstamp>5AFAF727</tstamp>
    </comp>
    <comp ref="C3.2">
      <value>100uF</value>
      <libsource lib="device" part="CP"/>
      <sheetpath names="/" tstamps="/"/>
      <tstamp>5AFAF728</tstamp>
    </comp>
    <comp ref="R5">
      <value>100K</value>
      <libsource lib="device" part="R"/>
      <sheetpath names="/" tstamps="/"/>
      <tstamp>5AFAF735</tstamp>
    </comp>
    <comp ref="Q7">
      <value>2N3904</value>
      <libsource lib="device" part="Q_NPN_CBE"/>
      <sheetpath names="/" tstamps="/"/>
      <tstamp>5AFAF736</tstamp>
    </comp>
    <comp ref="R12">
      <value>10K</value>
      <libsource lib="device" part="R"/>
      <sheetpath names="/" tstamps="/"/>
      <tstamp>5AFAF738</tstamp>
    </comp>
    <comp ref="D1">
      <value>12V Zener</value>
      <libsource lib="device" part="D_Zener_ALT"/>
      <sheetpath names="/" tstamps="/"/>
      <tstamp>5AFAF739</tstamp>
    </comp>
    <comp ref="R3">
      <value>10K</value>
      <libsource lib="device" part="R"/>
      <sheetpath names="/" tstamps="/"/>
      <tstamp>5AFAF73A</tstamp>
    </comp>
    <comp ref="R11">
      <value>47K</value>
      <libsource lib="device" part="R"/>
      <sheetpath names="/" tstamps="/"/>
      <tstamp>5AFAF73B</tstamp>
    </comp>
    <comp ref="C7">
      <value>10uF</value>
      <libsource lib="device" part="CP"/>
      <sheetpath names="/" tstamps="/"/>
      <tstamp>5AFAF73D</tstamp>
    </comp>
    <comp ref="R9">
      <value>10K</value>
      <libsource lib="device" part="R"/>
      <sheetpath names="/" tstamps="/"/>
      <tstamp>5AFAF73E</tstamp>
    </comp>
    <comp ref="Q5">
      <value>2N3904</value>
      <libsource lib="device" part="Q_NPN_CBE"/>
      <sheetpath names="/" tstamps="/"/>
      <tstamp>5AFAF740</tstamp>
    </comp>
    <comp ref="D3">
      <value>1N4148</value>
      <libsource lib="device" part="D_ALT"/>
      <sheetpath names="/" tstamps="/"/>
      <tstamp>5AFAF741</tstamp>
    </comp>
    <comp ref="Q2">
      <value>IRF4905</value>
      <footprint>TO-220</footprint>
      <libsource lib="Modules" part="IRF4905"/>
      <sheetpath names="/" tstamps="/"/>
      <tstamp>5AFBBBA6</tstamp>
    </comp>
    <comp ref="Q1">
      <value>IRF4905</value>
      <footprint>TO-220</footprint>
      <libsource lib="Modules" part="IRF4905"/>
      <sheetpath names="/" tstamps="/"/>
      <tstamp>5AFBD48B</tstamp>
    </comp>
    <comp ref="T1">
      <value>Mains Transformer</value>
      <libsource lib="device" part="Transformer_1P_1S"/>
      <sheetpath names="/" tstamps="/"/>
      <tstamp>5AFA9B9E</tstamp>
    </comp>
    <comp ref="L1">
      <value>31 turns 6*1mm T130 toroid</value>
      <libsource lib="device" part="L"/>
      <sheetpath names="/" tstamps="/"/>
      <tstamp>5AFCA8EC</tstamp>
    </comp>
    <comp ref="Q3">
      <value>IRF4905</value>
      <footprint>TO-220</footprint>
      <libsource lib="Modules" part="IRF4905"/>
      <sheetpath names="/" tstamps="/"/>
      <tstamp>5AFCDAB7</tstamp>
    </comp>
    <comp ref="Q6">
      <value>IRF4905</value>
      <footprint>TO-220</footprint>
      <libsource lib="Modules" part="IRF4905"/>
      <sheetpath names="/" tstamps="/"/>
      <tstamp>5AFCDD18</tstamp>
    </comp>
    <comp ref="D4">
      <value>MBR2045</value>
      <libsource lib="device" part="D_Schottky"/>
      <sheetpath names="/" tstamps="/"/>
      <tstamp>5AFCE1BE</tstamp>
    </comp>
    <comp ref="D5">
      <value>MBR2045</value>
      <libsource lib="device" part="D_Schottky"/>
      <sheetpath names="/" tstamps="/"/>
      <tstamp>5AFCE299</tstamp>
    </comp>
    <comp ref="D6">
      <value>MBR2045</value>
      <libsource lib="device" part="D_Schottky"/>
      <sheetpath names="/" tstamps="/"/>
      <tstamp>5AFCE378</tstamp>
    </comp>
    <comp ref="D7">
      <value>MBR2045</value>
      <libsource lib="device" part="D_Schottky"/>
      <sheetpath names="/" tstamps="/"/>
      <tstamp>5AFCE52C</tstamp>
    </comp>
    <comp ref="C8">
      <value>0.1uF</value>
      <libsource lib="device" part="C"/>
      <sheetpath names="/" tstamps="/"/>
      <tstamp>5AFCEF88</tstamp>
    </comp>
    <comp ref="R4">
      <value>180</value>
      <libsource lib="device" part="R"/>
      <sheetpath names="/" tstamps="/"/>
      <tstamp>5AFCF035</tstamp>
    </comp>
    <comp ref="C2.1">
      <value>100uF</value>
      <libsource lib="device" part="CP"/>
      <sheetpath names="/" tstamps="/"/>
      <tstamp>5AFD90EB</tstamp>
    </comp>
    <comp ref="C2.2">
      <value>100uF</value>
      <libsource lib="device" part="CP"/>
      <sheetpath names="/" tstamps="/"/>
      <tstamp>5AFD90F1</tstamp>
    </comp>
    <comp ref="C1.2">
      <value>100uF</value>
      <libsource lib="device" part="CP"/>
      <sheetpath names="/" tstamps="/"/>
      <tstamp>5AFDEE84</tstamp>
    </comp>
    <comp ref="C1.4">
      <value>100uF</value>
      <libsource lib="device" part="CP"/>
      <sheetpath names="/" tstamps="/"/>
      <tstamp>5AFDEE8A</tstamp>
    </comp>
    <comp ref="C1.6">
      <value>100uF</value>
      <libsource lib="device" part="CP"/>
      <sheetpath names="/" tstamps="/"/>
      <tstamp>5AFDEE90</tstamp>
    </comp>
    <comp ref="C1.8">
      <value>100uF</value>
      <libsource lib="device" part="CP"/>
      <sheetpath names="/" tstamps="/"/>
      <tstamp>5AFDEE96</tstamp>
    </comp>
    <comp ref="U2">
      <value>IR2110</value>
      <libsource lib="Modules" part="IR2110"/>
      <sheetpath names="/" tstamps="/"/>
      <tstamp>5AFE3AC3</tstamp>
    </comp>
    <comp ref="R7">
      <value>5R</value>
      <libsource lib="device" part="R"/>
      <sheetpath names="/" tstamps="/"/>
      <tstamp>5AFE436D</tstamp>
    </comp>
    <comp ref="U3">
      <value>IR2110</value>
      <libsource lib="Modules" part="IR2110"/>
      <sheetpath names="/" tstamps="/"/>
      <tstamp>5AFE479D</tstamp>
    </comp>
    <comp ref="R10">
      <value>5R</value>
      <libsource lib="device" part="R"/>
      <sheetpath names="/" tstamps="/"/>
      <tstamp>5AFE4885</tstamp>
    </comp>
    <comp ref="C4">
      <value>100nF</value>
      <libsource lib="device" part="C"/>
      <sheetpath names="/" tstamps="/"/>
      <tstamp>5AFE7C93</tstamp>
    </comp>
    <comp ref="C6">
      <value>100nF</value>
      <libsource lib="device" part="C"/>
      <sheetpath names="/" tstamps="/"/>
      <tstamp>5B02568E</tstamp>
    </comp>
    <comp ref="SW2">
      <value>RESET</value>
      <libsource lib="switches" part="SW_Push"/>
      <sheetpath names="/" tstamps="/"/>
      <tstamp>5AF7D21C</tstamp>
    </comp>
    <comp ref="R20">
      <value>1K</value>
      <libsource lib="device" part="R"/>
      <sheetpath names="/" tstamps="/"/>
      <tstamp>5AF7D228</tstamp>
    </comp>
    <comp ref="J8">
      <value>USB_B</value>
      <libsource lib="conn" part="USB_B"/>
      <sheetpath names="/" tstamps="/"/>
      <tstamp>5AF7C3A5</tstamp>
    </comp>
    <comp ref="R21">
      <value>220</value>
      <libsource lib="device" part="R"/>
      <sheetpath names="/" tstamps="/"/>
      <tstamp>5AF8786D</tstamp>
    </comp>
    <comp ref="R22">
      <value>220</value>
      <libsource lib="device" part="R"/>
      <sheetpath names="/" tstamps="/"/>
      <tstamp>5AF8797F</tstamp>
    </comp>
    <comp ref="Y1">
      <value>16MHz</value>
      <libsource lib="device" part="Crystal_Small"/>
      <sheetpath names="/" tstamps="/"/>
      <tstamp>5AFB8D62</tstamp>
    </comp>
    <comp ref="C10">
      <value>12pF</value>
      <libsource lib="device" part="C"/>
      <sheetpath names="/" tstamps="/"/>
      <tstamp>5AFBE9DE</tstamp>
    </comp>
    <comp ref="C11">
      <value>12pF</value>
      <libsource lib="device" part="C"/>
      <sheetpath names="/" tstamps="/"/>
      <tstamp>5AFBEAFD</tstamp>
    </comp>
    <comp ref="J6">
      <value>12VAC Screw Terminal</value>
      <libsource lib="conn" part="Screw_Terminal_01x02"/>
      <sheetpath names="/" tstamps="/"/>
      <tstamp>5AFC340B</tstamp>
    </comp>
  </components>
  <libparts>
    <libpart lib="Modules" part="ACS712module">
      <fields>
        <field name="Reference">U</field>
        <field name="Value">ACS712module</field>
      </fields>
      <pins>
        <pin num="1" name="IP+" type="BiDi"/>
        <pin num="2" name="IP+" type="BiDi"/>
        <pin num="3" name="IP-" type="BiDi"/>
        <pin num="4" name="IP-" type="BiDi"/>
        <pin num="5" name="GND" type="power_in"/>
        <pin num="6" name="FILTER" type="BiDi"/>
        <pin num="7" name="VIOUT" type="output"/>
        <pin num="8" name="VCC" type="power_in"/>
        <pin num="11" name="IP--" type="BiDi"/>
        <pin num="12" name="IP++" type="BiDi"/>
        <pin num="13" name="GND" type="power_in"/>
        <pin num="14" name="OUT" type="output"/>
        <pin num="15" name="VCC" type="power_in"/>
      </pins>
    </libpart>
    <libpart lib="atmel" part="ATMEGA168A-PU">
      <aliases>
        <alias>ATMEGA48A-PU</alias>
        <alias>ATMEGA48PA-PU</alias>
        <alias>ATMEGA88A-PU</alias>
        <alias>ATMEGA88PA-PU</alias>
        <alias>ATMEGA168PA-PU</alias>
        <alias>ATMEGA328-PU</alias>
        <alias>ATMEGA328P-PU</alias>
      </aliases>
      <description>PDIP28 Narrow, 16k Flash, 1kB SRAM, 512B EEPROM</description>
      <docs>http://www.atmel.com/images/atmel-8271-8-bit-avr-microcontroller-atmega48a-48pa-88a-88pa-168a-168pa-328-328p_datasheet.pdf</docs>
      <footprints>
        <fp>28DIP-ELL600</fp>
        <fp>28dip600</fp>
      </footprints>
      <fields>
        <field name="Reference">U</field>
        <field name="Value">ATMEGA168A-PU</field>
        <field name="Footprint">DIL28</field>
      </fields>
      <pins>
        <pin num="1" name="(PCINT14/~RESET~)PC6" type="BiDi"/>
        <pin num="2" name="(PCINT16/RXD)PD0" type="BiDi"/>
        <pin num="3" name="(PCINT17/TXD)PD1" type="BiDi"/>
        <pin num="4" name="(PCINT18/INT0)PD2" type="BiDi"/>
        <pin num="5" name="(PCINT19/OC2B/INT1)PD3" type="BiDi"/>
        <pin num="6" name="(PCINT20/XCK/T0)PD4" type="BiDi"/>
        <pin num="7" name="VCC" type="power_in"/>
        <pin num="8" name="GND" type="power_in"/>
        <pin num="9" name="(PCINT6/XTAL1/TOSC1)PB6" type="BiDi"/>
        <pin num="10" name="(PCINT7/XTAL2/TOSC2)PB7" type="BiDi"/>
        <pin num="11" name="(PCINT21/OC0B/T1)PD5" type="BiDi"/>
        <pin num="12" name="(PCINT22/OC0A/AIN0)PD6" type="BiDi"/>
        <pin num="13" name="(PCINT23/AIN1)PD7" type="BiDi"/>
        <pin num="14" name="(PCINT0/CLKO/ICP1)PB0" type="BiDi"/>
        <pin num="15" name="(PCINT1/OC1A)PB1" type="BiDi"/>
        <pin num="16" name="(PCINT2/OC1B/~SS~)PB2" type="BiDi"/>
        <pin num="17" name="(PCINT3/OC2A/MOSI)PB3" type="BiDi"/>
        <pin num="18" name="(PCINT4/MISO)PB4" type="BiDi"/>
        <pin num="19" name="(PCINT5/SCK)PB5" type="BiDi"/>
        <pin num="20" name="AVCC" type="power_in"/>
        <pin num="21" name="AREF" type="BiDi"/>
        <pin num="22" name="GND" type="power_in"/>
        <pin num="23" name="(PCINT8/ADC0)PC0" type="BiDi"/>
        <pin num="24" name="(PCINT9/ADC1)PC1" type="BiDi"/>
        <pin num="25" name="(PCINT10/ADC2)PC2" type="BiDi"/>
        <pin num="26" name="(PCINT11/ADC3)PC3" type="BiDi"/>
        <pin num="27" name="(PCINT12/SDA/ADC4)PC4" type="BiDi"/>
        <pin num="28" name="(PCINT13/SCL/ADC5)PC5" type="BiDi"/>
      </pins>
    </libpart>
    <libpart lib="device" part="Battery">
      <description>Battery (multiple cells)</description>
      <docs>~</docs>
      <fields>
        <field name="Reference">BT</field>
        <field name="Value">Battery</field>
      </fields>
      <pins>
        <pin num="1" name="+" type="passive"/>
        <pin num="2" name="-" type="passive"/>
      </pins>
    </libpart>
    <libpart lib="device" part="C">
      <description>Unpolarized capacitor</description>
      <footprints>
        <fp>C_*</fp>
      </footprints>
      <fields>
        <field name="Reference">C</field>
        <field name="Value">C</field>
      </fields>
      <pins>
        <pin num="1" name="~" type="passive"/>
        <pin num="2" name="~" type="passive"/>
      </pins>
    </libpart>
    <libpart lib="device" part="CP">
      <description>Polarised capacitor</description>
      <footprints>
        <fp>CP_*</fp>
      </footprints>
      <fields>
        <field name="Reference">C</field>
        <field name="Value">CP</field>
      </fields>
      <pins>
        <pin num="1" name="~" type="passive"/>
        <pin num="2" name="~" type="passive"/>
      </pins>
    </libpart>
    <libpart lib="device" part="Crystal_Small">
      <description>Two pin crystal, small symbol</description>
      <footprints>
        <fp>Crystal*</fp>
      </footprints>
      <fields>
        <field name="Reference">Y</field>
        <field name="Value">Crystal_Small</field>
      </fields>
      <pins>
        <pin num="1" name="1" type="passive"/>
        <pin num="2" name="2" type="passive"/>
      </pins>
    </libpart>
    <libpart lib="Modules" part="DS1307_RTC">
      <description>Realtime Clock/Calendar I2C Interface, DIP/SOIC/TSSOP-8</description>
      <docs>http://www.nxp.com/documents/data_sheet/PCF8563.pdf</docs>
      <footprints>
        <fp>DIP*</fp>
        <fp>PDIP*</fp>
        <fp>SOIC*</fp>
        <fp>SO*</fp>
        <fp>TSSOP*</fp>
      </footprints>
      <fields>
        <field name="Reference">U</field>
        <field name="Value">DS1307_RTC</field>
      </fields>
      <pins>
        <pin num="1" name="GND" type="power_in"/>
        <pin num="2" name="Vcc" type="power_in"/>
        <pin num="3" name="SDA" type="BiDi"/>
        <pin num="4" name="SCL" type="input"/>
        <pin num="5" name="DS" type="input"/>
        <pin num="6" name="SQ" type="output"/>
        <pin num="7" name="BAT" type="output"/>
      </pins>
    </libpart>
    <libpart lib="Modules" part="DS18B20">
      <fields>
        <field name="Reference">U</field>
        <field name="Value">DS18B20</field>
      </fields>
      <pins>
        <pin num="1" name="G" type="power_in"/>
        <pin num="2" name="DATA" type="BiDi"/>
        <pin num="3" name="Vcc" type="power_in"/>
      </pins>
    </libpart>
    <libpart lib="device" part="D_ALT">
      <description>Diode, alternativ symbol</description>
      <footprints>
        <fp>TO-???*</fp>
        <fp>*SingleDiode</fp>
        <fp>*_Diode_*</fp>
        <fp>*SingleDiode*</fp>
        <fp>D_*</fp>
      </footprints>
      <fields>
        <field name="Reference">D</field>
        <field name="Value">D_ALT</field>
      </fields>
      <pins>
        <pin num="1" name="K" type="passive"/>
        <pin num="2" name="A" type="passive"/>
      </pins>
    </libpart>
    <libpart lib="device" part="D_Bridge_+-AA">
      <description>Diode bridge (pins: 1=+, 2=-, 3=AC, 4=AC)</description>
      <footprints>
        <fp>D?Bridge*</fp>
        <fp>D?Rectifier*</fp>
      </footprints>
      <fields>
        <field name="Reference">D</field>
        <field name="Value">D_Bridge_+-AA</field>
      </fields>
      <pins>
        <pin num="1" name="+" type="input"/>
        <pin num="2" name="-" type="input"/>
        <pin num="3" name="~" type="input"/>
        <pin num="4" name="~" type="input"/>
      </pins>
    </libpart>
    <libpart lib="device" part="D_Schottky">
      <description>Schottky diode</description>
      <footprints>
        <fp>TO-???*</fp>
        <fp>*SingleDiode</fp>
        <fp>*_Diode_*</fp>
        <fp>*SingleDiode*</fp>
        <fp>D_*</fp>
      </footprints>
      <fields>
        <field name="Reference">D</field>
        <field name="Value">D_Schottky</field>
      </fields>
      <pins>
        <pin num="1" name="K" type="passive"/>
        <pin num="2" name="A" type="passive"/>
      </pins>
    </libpart>
    <libpart lib="device" part="D_TVS_ALT">
      <description>Bidirectional transient-voltage-suppression (TVS) diode, alternative symbol</description>
      <docs>https://en.wikipedia.org/wiki/Transient-voltage-suppression_diode</docs>
      <footprints>
        <fp>TO-???*</fp>
        <fp>*SingleDiode</fp>
        <fp>*_Diode_*</fp>
        <fp>*SingleDiode*</fp>
        <fp>D_*</fp>
      </footprints>
      <fields>
        <field name="Reference">D</field>
        <field name="Value">D_TVS_ALT</field>
      </fields>
      <pins>
        <pin num="1" name="A1" type="passive"/>
        <pin num="2" name="A2" type="passive"/>
      </pins>
    </libpart>
    <libpart lib="device" part="D_Zener_ALT">
      <description>Zener Diode, alternativ symbol</description>
      <docs>https://en.wikipedia.org/wiki/Zener_diode</docs>
      <footprints>
        <fp>TO-???*</fp>
        <fp>*SingleDiode</fp>
        <fp>*_Diode_*</fp>
        <fp>*SingleDiode*</fp>
        <fp>D_*</fp>
      </footprints>
      <fields>
        <field name="Reference">D</field>
        <field name="Value">D_Zener_ALT</field>
      </fields>
      <pins>
        <pin num="1" name="K" type="passive"/>
        <pin num="2" name="A" type="passive"/>
      </pins>
    </libpart>
    <libpart lib="device" part="Fuse">
      <description>Fuse, generic</description>
      <footprints>
        <fp>*Fuse*</fp>
      </footprints>
      <fields>
        <field name="Reference">F</field>
        <field name="Value">Fuse</field>
      </fields>
      <pins>
        <pin num="1" name="~" type="passive"/>
        <pin num="2" name="~" type="passive"/>
      </pins>
    </libpart>
    <libpart lib="Modules" part="IR2110">
      <fields>
        <field name="Reference">U</field>
        <field name="Value">IR2110</field>
      </fields>
      <pins>
        <pin num="1" name="LO" type="output"/>
        <pin num="2" name="COM" type="power_in"/>
        <pin num="3" name="Vcc" type="power_in"/>
        <pin num="4" name="~" type="NotConnected"/>
        <pin num="5" name="Vs" type="input"/>
        <pin num="6" name="VB" type="input"/>
        <pin num="7" name="HO" type="input"/>
        <pin num="8" name="~" type="NotConnected"/>
        <pin num="9" name="Vdd" type="power_in"/>
        <pin num="10" name="Hin" type="input"/>
        <pin num="11" name="SD" type="input"/>
        <pin num="12" name="Lin" type="input"/>
        <pin num="13" name="Vss" type="input"/>
        <pin num="14" name="~" type="NotConnected"/>
      </pins>
    </libpart>
    <libpart lib="Modules" part="IRF4905">
      <description>-60V Vds, -0.18A Id, P-Channel MOSFET, TO-92</description>
      <docs>http://www.vishay.com/docs/70209/70209.pdf</docs>
      <footprints>
        <fp>TO?92*</fp>
      </footprints>
      <fields>
        <field name="Reference">Q</field>
        <field name="Value">IRF4905</field>
        <field name="Footprint">TO-220</field>
      </fields>
      <pins>
        <pin num="1" name="D" type="passive"/>
        <pin num="2" name="G" type="input"/>
        <pin num="3" name="S" type="passive"/>
      </pins>
    </libpart>
    <libpart lib="device" part="L">
      <description>Inductor</description>
      <footprints>
        <fp>Choke_*</fp>
        <fp>*Coil*</fp>
        <fp>Inductor_*</fp>
        <fp>L_*</fp>
      </footprints>
      <fields>
        <field name="Reference">L</field>
        <field name="Value">L</field>
      </fields>
      <pins>
        <pin num="1" name="1" type="passive"/>
        <pin num="2" name="2" type="passive"/>
      </pins>
    </libpart>
    <libpart lib="Modules" part="LCDSerial2004">
      <description>LCD 20 wide 4 rows with I2C Serial Backpack</description>
      <fields>
        <field name="Reference">U</field>
        <field name="Value">LCDSerial2004</field>
      </fields>
      <pins>
        <pin num="1" name="Vcc" type="power_in"/>
        <pin num="2" name="SDA" type="input"/>
        <pin num="3" name="SCL" type="input"/>
        <pin num="4" name="GND" type="power_in"/>
      </pins>
    </libpart>
    <libpart lib="device" part="LED_ALT">
      <description>LED generic, alternativ symbol</description>
      <footprints>
        <fp>LED*</fp>
      </footprints>
      <fields>
        <field name="Reference">D</field>
        <field name="Value">LED_ALT</field>
      </fields>
      <pins>
        <pin num="1" name="K" type="passive"/>
        <pin num="2" name="A" type="passive"/>
      </pins>
    </libpart>
    <libpart lib="Modules" part="MP2307_DC-DC_module">
      <fields>
        <field name="Reference">U</field>
        <field name="Value">MP2307_DC-DC_module</field>
      </fields>
      <pins>
        <pin num="1" name="IN+" type="input"/>
        <pin num="2" name="IN-" type="input"/>
        <pin num="3" name="OUT-" type="input"/>
        <pin num="4" name="OUT+" type="input"/>
      </pins>
    </libpart>
    <libpart lib="device" part="Q_NPN_CBE">
      <description>Transistor NPN (general)</description>
      <fields>
        <field name="Reference">Q</field>
        <field name="Value">Q_NPN_CBE</field>
      </fields>
      <pins>
        <pin num="1" name="C" type="passive"/>
        <pin num="2" name="B" type="input"/>
        <pin num="3" name="E" type="passive"/>
      </pins>
    </libpart>
    <libpart lib="device" part="R">
      <description>Resistor</description>
      <footprints>
        <fp>R_*</fp>
        <fp>R_*</fp>
      </footprints>
      <fields>
        <field name="Reference">R</field>
        <field name="Value">R</field>
      </fields>
      <pins>
        <pin num="1" name="~" type="passive"/>
        <pin num="2" name="~" type="passive"/>
      </pins>
    </libpart>
    <libpart lib="Modules" part="SD_Micro_5V">
      <description>Micro SD Card Socket</description>
      <docs>http://katalog.we-online.de/em/datasheet/693072010801.pdf</docs>
      <fields>
        <field name="Reference">J</field>
        <field name="Value">SD_Micro_5V</field>
      </fields>
      <pins>
        <pin num="1" name="GND" type="BiDi"/>
        <pin num="2" name="VCC" type="BiDi"/>
        <pin num="3" name="MISO" type="input"/>
        <pin num="4" name="MOSI" type="power_in"/>
        <pin num="5" name="SCK" type="input"/>
        <pin num="6" name="CS" type="power_in"/>
      </pins>
    </libpart>
    <libpart lib="switches" part="SW_Push">
      <description>Push button switch, generic, two pins</description>
      <fields>
        <field name="Reference">SW</field>
        <field name="Value">SW_Push</field>
      </fields>
      <pins>
        <pin num="1" name="1" type="passive"/>
        <pin num="2" name="2" type="passive"/>
      </pins>
    </libpart>
    <libpart lib="conn" part="Screw_Terminal_01x02">
      <description>Generic screw terminal, single row, 01x02</description>
      <docs>~</docs>
      <footprints>
        <fp>Connector*Terminal*Block*:*</fp>
        <fp>TerminalBlock*</fp>
      </footprints>
      <fields>
        <field name="Reference">J</field>
        <field name="Value">Screw_Terminal_01x02</field>
      </fields>
      <pins>
        <pin num="1" name="Pin_1" type="passive"/>
        <pin num="2" name="Pin_2" type="passive"/>
      </pins>
    </libpart>
    <libpart lib="conn" part="Screw_Terminal_01x03">
      <description>Generic screw terminal, single row, 01x03</description>
      <docs>~</docs>
      <footprints>
        <fp>Connector*Terminal*Block*:*</fp>
        <fp>TerminalBlock*</fp>
      </footprints>
      <fields>
        <field name="Reference">J</field>
        <field name="Value">Screw_Terminal_01x03</field>
      </fields>
      <pins>
        <pin num="1" name="Pin_1" type="passive"/>
        <pin num="2" name="Pin_2" type="passive"/>
        <pin num="3" name="Pin_3" type="passive"/>
      </pins>
    </libpart>
    <libpart lib="device" part="Transformer_1P_1S">
      <description>Transformer, single primary, single secondary</description>
      <fields>
        <field name="Reference">T</field>
        <field name="Value">Transformer_1P_1S</field>
      </fields>
      <pins>
        <pin num="1" name="AA" type="passive"/>
        <pin num="2" name="AB" type="passive"/>
        <pin num="3" name="SA" type="passive"/>
        <pin num="4" name="SB" type="passive"/>
      </pins>
    </libpart>
    <libpart lib="conn" part="USB_B">
      <description>USB Type B connector</description>
      <footprints>
        <fp>USB*</fp>
      </footprints>
      <fields>
        <field name="Reference">J</field>
        <field name="Value">USB_B</field>
      </fields>
      <pins>
        <pin num="1" name="VBUS" type="power_out"/>
        <pin num="2" name="D-" type="passive"/>
        <pin num="3" name="D+" type="passive"/>
        <pin num="4" name="GND" type="power_out"/>
        <pin num="5" name="Shield" type="passive"/>
      </pins>
    </libpart>
  </libparts>
  <libraries>
    <library logical="atmel">
      <uri>/usr/share/kicad/library/atmel.lib</uri>
    </library>
    <library logical="Modules">
      <uri>/home/guy/aProjects/KiCAD/lib_sch/Modules.lib</uri>
    </library>
    <library logical="conn">
      <uri>/usr/share/kicad/library/conn.lib</uri>
    </library>
    <library logical="switches">
      <uri>/usr/share/kicad/library/switches.lib</uri>
    </library>
    <library logical="device">
      <uri>/usr/share/kicad/library/device.lib</uri>
    </library>
  </libraries>
  <nets>
    <net code="1" name="Net-(C8-Pad1)">
      <node ref="R4" pin="1"/>
      <node ref="C8" pin="1"/>
    </net>
    <net code="2" name="Net-(Q6-Pad2)">
      <node ref="R10" pin="1"/>
      <node ref="Q6" pin="2"/>
    </net>
    <net code="3" name="Net-(C8-Pad2)">
      <node ref="D5" pin="1"/>
      <node ref="Q3" pin="1"/>
      <node ref="D6" pin="1"/>
      <node ref="L1" pin="1"/>
      <node ref="D4" pin="1"/>
      <node ref="C8" pin="2"/>
      <node ref="D7" pin="1"/>
      <node ref="Q6" pin="1"/>
    </net>
    <net code="4" name="Arduino_pin_D9">
      <node ref="U2" pin="10"/>
      <node ref="D8" pin="2"/>
      <node ref="U3" pin="10"/>
      <node ref="U10" pin="15"/>
    </net>
    <net code="5" name="Net-(U2-Pad1)">
      <node ref="U2" pin="1"/>
    </net>
    <net code="6" name="Net-(U2-Pad4)">
      <node ref="U2" pin="4"/>
    </net>
    <net code="7" name="Net-(U2-Pad8)">
      <node ref="U2" pin="8"/>
    </net>
    <net code="8" name="Net-(U2-Pad14)">
      <node ref="U2" pin="14"/>
    </net>
    <net code="9" name="Net-(Q7-Pad1)">
      <node ref="Q7" pin="1"/>
      <node ref="R9" pin="2"/>
    </net>
    <net code="10" name="Net-(D3-Pad1)">
      <node ref="Q2" pin="2"/>
      <node ref="R5" pin="2"/>
      <node ref="R9" pin="1"/>
      <node ref="D3" pin="1"/>
    </net>
    <net code="11" name="Net-(C4-Pad1)">
      <node ref="R12" pin="1"/>
      <node ref="D8" pin="1"/>
      <node ref="C4" pin="1"/>
    </net>
    <net code="12" name="Net-(C3.1-Pad1)">
      <node ref="D9" pin="1"/>
      <node ref="R14" pin="2"/>
      <node ref="Q8" pin="3"/>
      <node ref="C3.2" pin="1"/>
      <node ref="C3.1" pin="1"/>
    </net>
    <net code="13" name="Net-(D9-Pad3)">
      <node ref="D9" pin="3"/>
      <node ref="J6" pin="2"/>
    </net>
    <net code="14" name="Net-(Q7-Pad2)">
      <node ref="R12" pin="2"/>
      <node ref="Q7" pin="2"/>
    </net>
    <net code="15" name="Net-(J4-Pad2)">
      <node ref="J4" pin="2"/>
      <node ref="T1" pin="2"/>
    </net>
    <net code="16" name="Net-(J4-Pad3)">
      <node ref="J4" pin="3"/>
      <node ref="T1" pin="1"/>
    </net>
    <net code="17" name="Net-(C2.1-Pad1)">
      <node ref="C2.1" pin="1"/>
      <node ref="Q8" pin="1"/>
      <node ref="Q1" pin="3"/>
      <node ref="L1" pin="2"/>
      <node ref="U2" pin="3"/>
      <node ref="U5" pin="11"/>
      <node ref="U3" pin="3"/>
      <node ref="C2.2" pin="1"/>
      <node ref="R4" pin="2"/>
    </net>
    <net code="18" name="Net-(J1-Pad1)">
      <node ref="J1" pin="1"/>
      <node ref="Q1" pin="1"/>
    </net>
    <net code="19" name="Net-(T1-Pad3)">
      <node ref="T1" pin="3"/>
    </net>
    <net code="20" name="Net-(T1-Pad4)">
      <node ref="T1" pin="4"/>
    </net>
    <net code="21" name="Net-(Q5-Pad1)">
      <node ref="Q5" pin="1"/>
      <node ref="R3" pin="2"/>
    </net>
    <net code="22" name="Net-(C7-Pad1)">
      <node ref="C7" pin="1"/>
    </net>
    <net code="23" name="Net-(D1-Pad2)">
      <node ref="Q5" pin="2"/>
      <node ref="R11" pin="1"/>
      <node ref="D1" pin="2"/>
    </net>
    <net code="24" name="Net-(R20-Pad2)">
      <node ref="R20" pin="2"/>
      <node ref="U10" pin="1"/>
      <node ref="SW2" pin="2"/>
    </net>
    <net code="25" name="Net-(C6-Pad1)">
      <node ref="U10" pin="21"/>
      <node ref="C6" pin="1"/>
    </net>
    <net code="26" name="+5V">
      <node ref="U7" pin="2"/>
      <node ref="U3" pin="9"/>
      <node ref="R20" pin="1"/>
      <node ref="J8" pin="1"/>
      <node ref="J5" pin="1"/>
      <node ref="U4" pin="3"/>
      <node ref="U2" pin="9"/>
      <node ref="U1" pin="15"/>
      <node ref="U8" pin="4"/>
      <node ref="U5" pin="15"/>
      <node ref="U9" pin="1"/>
      <node ref="U6" pin="3"/>
      <node ref="R17" pin="1"/>
      <node ref="U11" pin="2"/>
      <node ref="U10" pin="20"/>
      <node ref="U10" pin="7"/>
    </net>
    <net code="27" name="Net-(J8-Pad2)">
      <node ref="J8" pin="2"/>
      <node ref="R22" pin="2"/>
    </net>
    <net code="28" name="Net-(J8-Pad3)">
      <node ref="J8" pin="3"/>
      <node ref="R21" pin="2"/>
    </net>
    <net code="29" name="Net-(U3-Pad1)">
      <node ref="U3" pin="1"/>
    </net>
    <net code="30" name="Net-(U3-Pad4)">
      <node ref="U3" pin="4"/>
    </net>
    <net code="31" name="Net-(U3-Pad14)">
      <node ref="U3" pin="14"/>
    </net>
    <net code="32" name="Net-(U3-Pad8)">
      <node ref="U3" pin="8"/>
    </net>
    <net code="33" name="Net-(C11-Pad2)">
      <node ref="C11" pin="2"/>
      <node ref="U10" pin="10"/>
      <node ref="Y1" pin="1"/>
    </net>
    <net code="34" name="Net-(C10-Pad2)">
      <node ref="Y1" pin="2"/>
      <node ref="C10" pin="2"/>
      <node ref="U10" pin="9"/>
    </net>
    <net code="35" name="Net-(D9-Pad4)">
      <node ref="D9" pin="4"/>
      <node ref="J6" pin="1"/>
    </net>
    <net code="36" name="Arduino_pin_D0">
      <node ref="R21" pin="1"/>
      <node ref="U10" pin="2"/>
    </net>
    <net code="37" name="Arduino_pin_D1">
      <node ref="U10" pin="3"/>
      <node ref="R22" pin="1"/>
    </net>
    <net code="38" name="Net-(R10-Pad2)">
      <node ref="U3" pin="7"/>
      <node ref="R10" pin="2"/>
    </net>
    <net code="39" name="Net-(C7-Pad2)">
      <node ref="C7" pin="2"/>
      <node ref="U2" pin="5"/>
      <node ref="Q5" pin="3"/>
      <node ref="D3" pin="2"/>
      <node ref="U3" pin="5"/>
    </net>
    <net code="40" name="Net-(Q3-Pad2)">
      <node ref="Q3" pin="2"/>
      <node ref="R7" pin="1"/>
    </net>
    <net code="41" name="Net-(R7-Pad2)">
      <node ref="R7" pin="2"/>
      <node ref="U2" pin="7"/>
    </net>
    <net code="42" name="Net-(Q8-Pad2)">
      <node ref="Q8" pin="2"/>
      <node ref="Q9" pin="1"/>
      <node ref="R14" pin="1"/>
    </net>
    <net code="43" name="GND">
      <node ref="U8" pin="3"/>
      <node ref="U5" pin="13"/>
      <node ref="U8" pin="2"/>
      <node ref="D7" pin="2"/>
      <node ref="C1.1" pin="2"/>
      <node ref="U2" pin="2"/>
      <node ref="C1.3" pin="2"/>
      <node ref="C1.5" pin="2"/>
      <node ref="C1.7" pin="2"/>
      <node ref="U10" pin="22"/>
      <node ref="SW1" pin="1"/>
      <node ref="D4" pin="2"/>
      <node ref="Q7" pin="3"/>
      <node ref="Q4" pin="3"/>
      <node ref="C5" pin="2"/>
      <node ref="C3.2" pin="2"/>
      <node ref="D5" pin="2"/>
      <node ref="U9" pin="4"/>
      <node ref="C3.1" pin="2"/>
      <node ref="U11" pin="1"/>
      <node ref="D6" pin="2"/>
      <node ref="U4" pin="1"/>
      <node ref="J5" pin="3"/>
      <node ref="C1.4" pin="2"/>
      <node ref="C1.6" pin="2"/>
      <node ref="C1.2" pin="2"/>
      <node ref="D2" pin="2"/>
      <node ref="J1" pin="2"/>
      <node ref="BT1" pin="2"/>
      <node ref="J7" pin="1"/>
      <node ref="U2" pin="11"/>
      <node ref="U2" pin="12"/>
      <node ref="U2" pin="13"/>
      <node ref="U1" pin="13"/>
      <node ref="J2" pin="2"/>
      <node ref="J3" pin="2"/>
      <node ref="D10" pin="1"/>
      <node ref="R6" pin="2"/>
      <node ref="C9" pin="2"/>
      <node ref="C1.8" pin="2"/>
      <node ref="U10" pin="8"/>
      <node ref="C11" pin="1"/>
      <node ref="C10" pin="1"/>
      <node ref="R11" pin="2"/>
      <node ref="U6" pin="1"/>
      <node ref="C4" pin="2"/>
      <node ref="J4" pin="1"/>
      <node ref="C6" pin="2"/>
      <node ref="J8" pin="5"/>
      <node ref="J8" pin="4"/>
      <node ref="U3" pin="2"/>
      <node ref="SW2" pin="1"/>
      <node ref="U3" pin="11"/>
      <node ref="U3" pin="12"/>
      <node ref="U3" pin="13"/>
      <node ref="C2.1" pin="2"/>
      <node ref="C2.2" pin="2"/>
      <node ref="U7" pin="1"/>
      <node ref="Q9" pin="3"/>
      <node ref="D9" pin="2"/>
    </net>
    <net code="44" name="Net-(Q9-Pad2)">
      <node ref="Q9" pin="2"/>
      <node ref="R15" pin="1"/>
    </net>
    <net code="45" name="Arduino_pin_D3">
      <node ref="U10" pin="5"/>
      <node ref="R15" pin="2"/>
    </net>
    <net code="46" name="Net-(U5-Pad1)">
      <node ref="U5" pin="1"/>
    </net>
    <net code="47" name="Net-(U5-Pad2)">
      <node ref="U5" pin="2"/>
    </net>
    <net code="48" name="Net-(U5-Pad3)">
      <node ref="U5" pin="3"/>
    </net>
    <net code="49" name="Net-(U5-Pad4)">
      <node ref="U5" pin="4"/>
    </net>
    <net code="50" name="Net-(U5-Pad5)">
      <node ref="U5" pin="5"/>
    </net>
    <net code="51" name="Net-(U5-Pad6)">
      <node ref="U5" pin="6"/>
    </net>
    <net code="52" name="Net-(U5-Pad7)">
      <node ref="U5" pin="7"/>
    </net>
    <net code="53" name="Net-(U5-Pad8)">
      <node ref="U5" pin="8"/>
    </net>
    <net code="54" name="Net-(Q1-Pad2)">
      <node ref="R1" pin="1"/>
      <node ref="Q4" pin="1"/>
      <node ref="Q1" pin="2"/>
    </net>
    <net code="55" name="Net-(R1-Pad2)">
      <node ref="R1" pin="2"/>
    </net>
    <net code="56" name="Net-(Q4-Pad2)">
      <node ref="R8" pin="1"/>
      <node ref="Q4" pin="2"/>
    </net>
    <net code="57" name="Arduino_pin_D4">
      <node ref="R8" pin="2"/>
      <node ref="U10" pin="6"/>
    </net>
    <net code="58" name="Arduino_pin_A2">
      <node ref="U10" pin="25"/>
      <node ref="R16" pin="1"/>
      <node ref="R13" pin="2"/>
      <node ref="C5" pin="1"/>
    </net>
    <net code="59" name="Arduino_pin_A3">
      <node ref="U5" pin="14"/>
      <node ref="U10" pin="26"/>
    </net>
    <net code="60" name="Arduino_pin_A4">
      <node ref="U10" pin="27"/>
      <node ref="U7" pin="3"/>
      <node ref="U9" pin="2"/>
    </net>
    <net code="61" name="Net-(R16-Pad2)">
      <node ref="R16" pin="2"/>
    </net>
    <net code="62" name="Net-(F1-Pad1)">
      <node ref="U8" pin="1"/>
      <node ref="U5" pin="12"/>
      <node ref="R13" pin="1"/>
      <node ref="F1" pin="1"/>
    </net>
    <net code="63" name="Net-(U1-Pad3)">
      <node ref="U1" pin="3"/>
    </net>
    <net code="64" name="Net-(U1-Pad1)">
      <node ref="U1" pin="1"/>
    </net>
    <net code="65" name="Net-(U1-Pad2)">
      <node ref="U1" pin="2"/>
    </net>
    <net code="66" name="Net-(C1.1-Pad1)">
      <node ref="R5" pin="1"/>
      <node ref="Q2" pin="3"/>
      <node ref="Q3" pin="3"/>
      <node ref="Q6" pin="3"/>
      <node ref="C1.3" pin="1"/>
      <node ref="C1.5" pin="1"/>
      <node ref="C1.1" pin="1"/>
      <node ref="C1.7" pin="1"/>
      <node ref="C1.6" pin="1"/>
      <node ref="C1.4" pin="1"/>
      <node ref="C1.2" pin="1"/>
      <node ref="C1.8" pin="1"/>
    </net>
    <net code="67" name="Net-(U1-Pad4)">
      <node ref="U1" pin="4"/>
    </net>
    <net code="68" name="Net-(U1-Pad5)">
      <node ref="U1" pin="5"/>
    </net>
    <net code="69" name="Net-(U1-Pad6)">
      <node ref="U1" pin="6"/>
    </net>
    <net code="70" name="Net-(U1-Pad7)">
      <node ref="U1" pin="7"/>
    </net>
    <net code="71" name="Net-(U1-Pad8)">
      <node ref="U1" pin="8"/>
    </net>
    <net code="72" name="Net-(D1-Pad1)">
      <node ref="U1" pin="12"/>
      <node ref="R3" pin="1"/>
      <node ref="U2" pin="6"/>
      <node ref="Q2" pin="1"/>
      <node ref="U3" pin="6"/>
      <node ref="D1" pin="1"/>
    </net>
    <net code="73" name="Arduino_pin_A1">
      <node ref="U10" pin="24"/>
      <node ref="U1" pin="14"/>
    </net>
    <net code="74" name="Net-(D2-Pad1)">
      <node ref="J2" pin="1"/>
      <node ref="U1" pin="11"/>
      <node ref="R2" pin="1"/>
      <node ref="D2" pin="1"/>
    </net>
    <net code="75" name="Net-(BT1-Pad1)">
      <node ref="BT1" pin="1"/>
      <node ref="F1" pin="2"/>
      <node ref="J3" pin="1"/>
    </net>
    <net code="76" name="Arduino_pin_A0">
      <node ref="C9" pin="1"/>
      <node ref="U10" pin="23"/>
      <node ref="R2" pin="2"/>
      <node ref="R6" pin="1"/>
    </net>
    <net code="77" name="Arduino_pin_A5">
      <node ref="U9" pin="3"/>
      <node ref="U7" pin="4"/>
      <node ref="U10" pin="28"/>
    </net>
    <net code="78" name="Net-(D11-Pad1)">
      <node ref="D11" pin="1"/>
    </net>
    <net code="79" name="Arduino_pin_D5">
      <node ref="U10" pin="11"/>
      <node ref="R18" pin="1"/>
    </net>
    <net code="80" name="Net-(D11-Pad2)">
      <node ref="J7" pin="2"/>
      <node ref="R19" pin="2"/>
      <node ref="D11" pin="2"/>
    </net>
    <net code="81" name="Net-(D10-Pad2)">
      <node ref="R18" pin="2"/>
      <node ref="J7" pin="3"/>
      <node ref="D10" pin="2"/>
    </net>
    <net code="82" name="Arduino_pin_D6">
      <node ref="R19" pin="1"/>
      <node ref="U10" pin="12"/>
    </net>
    <net code="83" name="Net-(U10-Pad16)">
      <node ref="U10" pin="16"/>
    </net>
    <net code="84" name="Arduino_pin_D11">
      <node ref="U10" pin="17"/>
      <node ref="U11" pin="4"/>
    </net>
    <net code="85" name="Arduino_pin_D7">
      <node ref="U10" pin="13"/>
      <node ref="R17" pin="2"/>
      <node ref="SW1" pin="2"/>
    </net>
    <net code="86" name="Arduino_pin_D8">
      <node ref="U10" pin="14"/>
      <node ref="U11" pin="6"/>
    </net>
    <net code="87" name="Net-(U7-Pad7)">
      <node ref="U7" pin="7"/>
    </net>
    <net code="88" name="Arduino_pin_D12">
      <node ref="U10" pin="18"/>
      <node ref="U11" pin="3"/>
    </net>
    <net code="89" name="Arduino_pin_D13">
      <node ref="U11" pin="5"/>
      <node ref="U10" pin="19"/>
    </net>
    <net code="90" name="Net-(U7-Pad6)">
      <node ref="U7" pin="6"/>
    </net>
    <net code="91" name="Arduino_pin_D2">
      <node ref="U7" pin="5"/>
      <node ref="U10" pin="4"/>
      <node ref="J5" pin="2"/>
      <node ref="U4" pin="2"/>
      <node ref="U6" pin="2"/>
    </net>
  </nets>
</export>
